pynprimos/__init__.py
pynprimos-1.0.dist-info/LICENSE
pynprimos-1.0.dist-info/METADATA
pynprimos-1.0.dist-info/WHEEL
pynprimos-1.0.dist-info/top_level.txt
pynprimos-1.0.dist-info/RECORD
